vnsdata/__init__.py
vnsdata/data.py
vnsdata/headers.py
vnsdata/lib.py
vnsdata-0.0.1.dist-info/METADATA
vnsdata-0.0.1.dist-info/WHEEL
vnsdata-0.0.1.dist-info/top_level.txt
vnsdata-0.0.1.dist-info/RECORD
