Metadata-Version: 2.1
Name: vnsdata
Version: 0.0.1
Summary: A simple Python package to take data and backtest trading strategy in Vietnam stocks market
Author: the-a1pha
Author-email: buitruonganad@gmail.com
